ip_area/__init__.py
ip_area/api.py
ip_area/ip_area.py
ip_area/tools.py
ip_area/version.py
ip_area/wrap_api.py
test/__init__.py
test/test.py
test/test_get_info.py
ip_area-0.0.1.dist-info/METADATA
ip_area-0.0.1.dist-info/WHEEL
ip_area-0.0.1.dist-info/top_level.txt
ip_area-0.0.1.dist-info/zip-safe
ip_area-0.0.1.dist-info/RECORD
