Metadata-Version: 2.1
Name: ip-area
Version: 0.0.1
Summary: ip area info
Home-page: https://github.com/mouday/ip-area
Author: Peng Shiyu
Author-email: pengshiyuyx@gmail.com
License: MIT
Keywords: ip,area
Platform: UNKNOWN
Classifier: Programming Language :: Python :: 3
Classifier: Programming Language :: Python :: 3.6
Requires-Dist: six
Requires-Dist: requests
